Metadata-Version: 2.1
Name: odoo14-addon-l10n-fi-edicode
Version: 14.0.1.0.1
Summary: Adds EDI code field and operators
Home-page: https://github.com/OCA/l10n-finland
Author: Tawasta, Odoo Community Association (OCA), Avoin.Systems
Author-email: support@odoo-community.org
License: LGPL-3
Platform: UNKNOWN
Classifier: Programming Language :: Python
Classifier: Framework :: Odoo
Classifier: Framework :: Odoo :: 14.0
Classifier: License :: OSI Approved :: GNU Lesser General Public License v3 (LGPLv3)
Requires-Python: >=3.6
Requires-Dist: odoo <14.1dev,>=14.0a
